aws_utils.py
aws_utils_vitalii_bozadzhy-0.1.0.dist-info/METADATA
aws_utils_vitalii_bozadzhy-0.1.0.dist-info/WHEEL
aws_utils_vitalii_bozadzhy-0.1.0.dist-info/top_level.txt
aws_utils_vitalii_bozadzhy-0.1.0.dist-info/RECORD
